Workbook

Sheet Overview
A1: Sistem Pengurusan Masjid Johor: System architecture
A2: Companion workbook to the layered architecture and hosting diagrams (Sept 2026). Proposal for discussion, not a final design.
A4: Purpose
A5: Inventory of the platform's components, technology choices, integrations, phasing and design decisions, so the architecture can be filtered, reviewed and costed.
A7: Component counts (formulas read from the Components sheet)
A8: By category | B8: Count
A9: Revenue module | B9: =COUNTIF(Components!$F$5:$F$38,A9) -> 3
A10: Governance module | B10: =COUNTIF(Components!$F$5:$F$38,A10) -> 6
A11: Platform and data | B11: =COUNTIF(Components!$F$5:$F$38,A11) -> 12
A12: External system | B12: =COUNTIF(Components!$F$5:$F$38,A12) -> 4
A13: Hosting and operations | B13: =COUNTIF(Components!$F$5:$F$38,A13) -> 8
A14: Security layer | B14: =COUNTIF(Components!$F$5:$F$38,A14) -> 1
A15: Total components | B15: =SUM(B9:B14) -> 34
A16: Check: total equals row count of Components | B16: =IF(B15=COUNTA(Components!$A$5:$A$38),"OK","MISMATCH") -> OK
A18: By layer
A19: Layer | B19: Count
A20: Channels | B20: =COUNTIF(Components!$B$5:$B$38,A20) -> 4
A21: Edge | B21: =COUNTIF(Components!$B$5:$B$38,A21) -> 1
A22: Application services | B22: =COUNTIF(Components!$B$5:$B$38,A22) -> 8
A23: Platform services | B23: =COUNTIF(Components!$B$5:$B$38,A23) -> 4
A24: Data | B24: =COUNTIF(Components!$B$5:$B$38,A24) -> 4
A25: External systems | B25: =COUNTIF(Components!$B$5:$B$38,A25) -> 4
A26: Hosting | B26: =COUNTIF(Components!$B$5:$B$38,A26) -> 8
A27: Security | B27: =COUNTIF(Components!$B$5:$B$38,A27) -> 1
A28: Total | B28: =SUM(B20:B27) -> 34
A30: Sheet guide
A31: Components | B31: All 34 boxes from the two diagrams, with layer, category, phase and basis
A32: Tech Stack | B32: Suggested technologies by layer, with rationale and alternatives
A33: Integrations | B33: External systems the platform connects to
A34: Phasing | B34: Component count and scope by delivery phase (formulas)
A35: Design Notes | B35: Key architecture decisions and why
A37: Colour key (Category column on Components)
A38: Revenue module
A39: Governance module
A40: Platform and data
A41: External system
A42: Hosting and operations
A43: Security layer

Sheet Components
A1: Component inventory
A2: Every box in the two architecture diagrams. Phase column is filterable. Source: system architecture answer (Sept 2026).
A4: ID | B4: Layer | C4: Component | D4: Sub-label | E4: Role | F4: Category | G4: Phase | H4: Phase basis
A5: C01 | B5: Channels | C5: Mosque portal | D5: Admin web app | E5: Web app for mosque admins, secretaries and treasurers: records, finance, programs | F5: Platform and data | G5: Phase 1 | H5: Stated
A6: C02 | B6: Channels | C6: Jemaah app | D6: Mobile web, PWA | E6: Donations, qurban orders, Quran class booking, public transparency pages | F6: Platform and data | G6: Phase 2 | H6: Assumption
A7: C03 | B7: Channels | C7: JAINJ console | D7: Oversight views | E7: State and district dashboards, scores, alerts (basic views first, full scoring views in Phase 3) | F7: Platform and data | G7: Phase 1 | H7: Assumption
A8: C04 | B8: Channels | C8: Tutor app | D8: Slots, payouts | E8: Ustaz and ustazah manage availability, bookings and payouts | F8: Platform and data | G8: Phase 2 | H8: Assumption
A9: E01 | B9: Edge | C9: API gateway, WAF and identity | D9: SSO, MFA, role-based access | E9: Single entry point and one identity model for all roles; MFA for officer roles | F9: Platform and data | G9: Phase 1 | H9: Stated
A10: S01 | B10: Application services | C10: Registry | D10: Mosques, AJK | E10: Mosque profiles, committee terms and members, officers, meetings | F10: Governance module | G10: Phase 1 | H10: Stated
A11: S02 | B11: Application services | C11: Finance | D11: Ledger, reports | E11: Income and expense ledger, monthly report workflow, audit records | F11: Governance module | G11: Phase 1 | H11: Stated
A12: S03 | B12: Application services | C12: Maintenance | D12: Assets, repairs | E12: Asset register, maintenance requests, inspections | F12: Governance module | G12: Phase 1 | H12: Stated
A13: S04 | B13: Application services | C13: Projects | D13: Renovation | E13: Renovation proposals, approval workflow, budget vs actual | F13: Governance module | G13: Phase 2 | H13: Assumption (matches business plan phasing)
A14: S05 | B14: Application services | C14: Kuliah | D14: Programs | E14: Scheduling, kuliah types, speaker tauliah checks, attendance | F14: Governance module | G14: Phase 1 | H14: Stated
A15: S06 | B15: Application services | C15: Donations | D15: QR, FPX, cards | E15: Campaigns, recurring gifts, reconciliation to TPMJ | F15: Revenue module | G15: Phase 2 | H15: Stated
... A38: SEC1 | B38: Security | C38: Security and compliance | D38: KMS, MFA, PDPA, pen tests | E38: Key management, MFA, PDPA controls, penetration testing | F38: Security layer | G38: Phase 1 | H38: Stated
A40: Phase basis: 'Stated' = phase given in the architecture answer. 'Assumption' = consultant's placement, aligned to the business plan phasing; confirm in Phase 0.

Sheet Tech Stack
A1: Suggested technology stack
A2: All choices are suggestions and replaceable; none is a requirement. To be confirmed during Phase 0 vendor selection.
A4: Layer | B4: Suggested choice | C4: Why | D4: Alternatives to consider
A5: Web and mobile | B5: React or Next.js as a PWA, Bahasa Melayu first | C5: One codebase for volunteers' phones and desktops; works on weak connections | D5: Vue or Angular PWA; native apps later for the Jemaah and Tutor channels
A6: Backend | B6: Node.js (NestJS) or Java (Spring Boot), modular monolith | C6: Common skills in Malaysia; easy to split into services later | D6: Python (Django), .NET
A7: Database | B7: PostgreSQL | C7: Matches the schema already delivered; strong transaction integrity for finance | D7: Managed PostgreSQL from the chosen cloud region
A8: Cache and jobs | B8: Redis with a job queue | C8: Receipts, reminders and monthly scoring runs | D8: Managed queue service of the chosen cloud
A9: Hosting | B9: Government-approved cloud region in Malaysia; containers; infrastructure as code | C9: Data residency and repeatable deployments | D9: Government data centre or private cloud, subject to state ICT requirements
A10: Payments | B10: Licensed payment gateway with split settlement | C10: Funds go to the mosque or tutor directly and platform commission is deducted at source, so PIJ Holdings or the SPV never holds donor money | D10: Two gateways for redundancy (one primary, one fallback)

Sheet Integrations
A1: External integrations
A2: Data exchanged and open points are proposals to be confirmed in Phase 0.
A4: System | B4: Direction | C4: Purpose | D4: Data exchanged (proposed) | E4: Phase | F4: Key dependency or open point
A5: Payment gateway | B5: Two-way | C5: Take donations, qurban and Quran booking payments (DuitNow QR, FPX, cards) | D5: Payment requests, status callbacks, settlement files | E5: Phase 2 | F5: Licensed gateway with split settlement; settlement to mosque or tutor accounts, never through PIJ Holdings
A6: TPMJ | B6: Two-way | C6: Reconcile online donations with the state fund | D6: Donation records, reconciliation reports | E6: Phase 2 | F6: Integration terms and any exclusivity on collection channels to be confirmed
A7: JAINJ data | B7: Mostly inbound | C7: Master data for mosques and speaker credentials | D7: Registered mosque list, tauliah holders | E7: Phase 1 | F7: Ownership of the authoritative tauliah list and whether an API exists
A8: Messaging | B8: Mostly outbound | C8: Deliver reminders, receipts and alerts | D8: SMS and WhatsApp messages, delivery status | E8: Phase 1 | F8: Provider selection; message templates and consent

Sheet Phasing
A1: Delivery phasing
A2: Component counts are formulas on the Components sheet. Phases align with the business plan (core pilot, money and community, scoring).
A4: Phase | B4: Aligned business plan phase | C4: Scope in this phase | D4: Components (count) | E4: Cumulative components
A5: Phase 1 | B5: Core pilot | C5: Registry, Finance, Maintenance, Kuliah, gateway and identity, core data stores, hosting and security baseline | D5: =COUNTIF(Components!$G$5:$G$38,A5) -> 23 | E5: =SUM($D$5:D5) -> 23
A6: Phase 2 | B6: Money and community | C6: Donations, Qurban, Quran booking, Projects (renovation), payment and TPMJ integrations, Jemaah and Tutor apps, DR site | D6: =COUNTIF(Components!$G$5:$G$38,A6) -> 9 | E6: =SUM($D$5:D6) -> 32
A7: Phase 3 | B7: Scoring and scale-up | C7: Scoring engine and analytics store | D7: =COUNTIF(Components!$G$5:$G$38,A7) -> 2 | E7: =SUM($D$5:D7) -> 34
A8: Total | D8: =SUM(D5:D7) -> 34
A9: Check | D9: =IF(D8=COUNTA(Components!$A$5:$A$38),"OK","MISMATCH") -> OK
A11: Placement of Projects, channels, notifications, documents, audit trail and the DR site is a consultant assumption aligned to the business plan; see Phase basis on Components.

Sheet Design Notes
A1: Key design decisions
A2: From the architecture answer. Rationale is the consultant's; for review with the technical team.
A4: # | B4: Topic | C4: Decision | D4: Rationale
A5: 1 | B5: Deployment style | C5: Modular monolith first: run the eight services as modules of one deployable application during the pilot | D5: Cheaper to build and operate; split Donations and Quran booking into separate services only when Ramadan and qurban traffic justify it
A6: 2 | B6: Identity | C6: One identity model for mosque admins, district officers, JAINJ officers, auditors, jemaah and tutors, with role-based access; MFA for officer roles | D6: Single place to manage access and audit it
A7: 3 | B7: Scoring isolation | C7: The Scoring engine reads other services' data and writes only to the Analytics DB | D7: A scoring error can never corrupt a mosque's financial records
A8: 4 | B8: Funds handling | C8: Payments settle through a licensed gateway with split settlement; platform commission deducted at source | D8: PIJ Holdings or the SPV never holds donor or tutor money
A9: 5 | B9: Quran booking | C9: Slot engine locks a time slot while a parent pays; pricing is hourly rate multiplied by hours, with a tier by number of students; tutors vetted for tauliah or equivalent before listing; guardian consent step for bookings with minors | D9: Prevents double booking, supports the by-the-hour and by-students billing, and addresses safeguarding
A10: 6 | B10: Peak load | C10: Autoscaling, a change freeze before Ramadan and qurban cutoffs, load tests in Phase 1 | D10: Traffic spikes on Fridays, in Ramadan and before qurban cutoffs
A11: 7 | B11: Availability | C11: Target 99.5% availability | D11: Figure carried over from the business plan
A12: 8 | B12: Data residency | C12: Hosting in a Malaysian cloud region so data stays in-country; DR in a second region | D12: Government and PDPA expectations; exact requirements to be confirmed in Phase 0
A13: 9 | B13: Phasing | C13: Phase 1 core governance modules and data stores; Phase 2 revenue modules; Phase 3 scoring and analytics | D13: Matches the funding gates in the business plan
